{
  "hash": "25274592",
  "browserHash": "33dd9f26",
  "optimized": {
    "react": {
      "src": "../../node_modules/react/index.js",
      "file": "react.js",
      "fileHash": "337b786f",
      "needsInterop": true
    },
    "react/jsx-dev-runtime": {
      "src": "../../node_modules/react/jsx-dev-runtime.js",
      "file": "react_jsx-dev-runtime.js",
      "fileHash": "341752c8",
      "needsInterop": true
    },
    "react/jsx-runtime": {
      "src": "../../node_modules/react/jsx-runtime.js",
      "file": "react_jsx-runtime.js",
      "fileHash": "a7494947",
      "needsInterop": true
    },
    "@chakra-ui/anatomy": {
      "src": "../../node_modules/@chakra-ui/anatomy/dist/index.mjs",
      "file": "@chakra-ui_anatomy.js",
      "fileHash": "80bcdaab",
      "needsInterop": false
    },
    "@chakra-ui/icons": {
      "src": "../../node_modules/@chakra-ui/icons/dist/index.mjs",
      "file": "@chakra-ui_icons.js",
      "fileHash": "8f2ed444",
      "needsInterop": false
    },
    "@chakra-ui/react": {
      "src": "../../node_modules/@chakra-ui/react/dist/index.mjs",
      "file": "@chakra-ui_react.js",
      "fileHash": "5e84e49c",
      "needsInterop": false
    },
    "@fuel-ts/providers": {
      "src": "../../node_modules/@fuel-ts/providers/dist/index.mjs",
      "file": "@fuel-ts_providers.js",
      "fileHash": "6bf436e8",
      "needsInterop": false
    },
    "@hookform/resolvers/yup": {
      "src": "../../node_modules/@hookform/resolvers/yup/dist/yup.mjs",
      "file": "@hookform_resolvers_yup.js",
      "fileHash": "712acd2a",
      "needsInterop": false
    },
    "axios": {
      "src": "../../node_modules/axios/index.js",
      "file": "axios.js",
      "fileHash": "61947e4e",
      "needsInterop": false
    },
    "bsafe": {
      "src": "../../node_modules/bsafe/dist/esm/index.js",
      "file": "bsafe.js",
      "fileHash": "ad7836f0",
      "needsInterop": false
    },
    "date-fns": {
      "src": "../../node_modules/date-fns/esm/index.js",
      "file": "date-fns.js",
      "fileHash": "64fe3b62",
      "needsInterop": false
    },
    "fuels": {
      "src": "../../node_modules/fuels/dist/index.mjs",
      "file": "fuels.js",
      "fileHash": "6a33a20d",
      "needsInterop": false
    },
    "js-cookie": {
      "src": "../../node_modules/js-cookie/dist/js.cookie.mjs",
      "file": "js-cookie.js",
      "fileHash": "c88be372",
      "needsInterop": false
    },
    "lodash.debounce": {
      "src": "../../node_modules/lodash.debounce/index.js",
      "file": "lodash__debounce.js",
      "fileHash": "f5d3963e",
      "needsInterop": true
    },
    "qrcode.react": {
      "src": "../../node_modules/qrcode.react/lib/esm/index.js",
      "file": "qrcode__react.js",
      "fileHash": "e21132cb",
      "needsInterop": false
    },
    "react-dom/client": {
      "src": "../../node_modules/react-dom/client.js",
      "file": "react-dom_client.js",
      "fileHash": "bb6aba38",
      "needsInterop": true
    },
    "react-hook-form": {
      "src": "../../node_modules/react-hook-form/dist/index.esm.mjs",
      "file": "react-hook-form.js",
      "fileHash": "c6a24419",
      "needsInterop": false
    },
    "react-icons/bs": {
      "src": "../../node_modules/react-icons/bs/index.esm.js",
      "file": "react-icons_bs.js",
      "fileHash": "eb6b5557",
      "needsInterop": false
    },
    "react-icons/cg": {
      "src": "../../node_modules/react-icons/cg/index.esm.js",
      "file": "react-icons_cg.js",
      "fileHash": "a51a49bb",
      "needsInterop": false
    },
    "react-icons/fa": {
      "src": "../../node_modules/react-icons/fa/index.esm.js",
      "file": "react-icons_fa.js",
      "fileHash": "2d44b4d0",
      "needsInterop": false
    },
    "react-icons/fi": {
      "src": "../../node_modules/react-icons/fi/index.esm.js",
      "file": "react-icons_fi.js",
      "fileHash": "47a6575c",
      "needsInterop": false
    },
    "react-icons/go": {
      "src": "../../node_modules/react-icons/go/index.esm.js",
      "file": "react-icons_go.js",
      "fileHash": "5d7114aa",
      "needsInterop": false
    },
    "react-icons/hi2": {
      "src": "../../node_modules/react-icons/hi2/index.esm.js",
      "file": "react-icons_hi2.js",
      "fileHash": "5fb95b32",
      "needsInterop": false
    },
    "react-icons/im": {
      "src": "../../node_modules/react-icons/im/index.esm.js",
      "file": "react-icons_im.js",
      "fileHash": "00c7001b",
      "needsInterop": false
    },
    "react-icons/io": {
      "src": "../../node_modules/react-icons/io/index.esm.js",
      "file": "react-icons_io.js",
      "fileHash": "620d541a",
      "needsInterop": false
    },
    "react-icons/io5": {
      "src": "../../node_modules/react-icons/io5/index.esm.js",
      "file": "react-icons_io5.js",
      "fileHash": "394ab01c",
      "needsInterop": false
    },
    "react-icons/md": {
      "src": "../../node_modules/react-icons/md/index.esm.js",
      "file": "react-icons_md.js",
      "fileHash": "40df5ea5",
      "needsInterop": false
    },
    "react-icons/si": {
      "src": "../../node_modules/react-icons/si/index.esm.js",
      "file": "react-icons_si.js",
      "fileHash": "9d739303",
      "needsInterop": false
    },
    "react-intersection-observer": {
      "src": "../../node_modules/react-intersection-observer/index.mjs",
      "file": "react-intersection-observer.js",
      "fileHash": "6029d355",
      "needsInterop": false
    },
    "react-query": {
      "src": "../../node_modules/react-query/es/index.js",
      "file": "react-query.js",
      "fileHash": "1a51b17c",
      "needsInterop": false
    },
    "react-query/devtools": {
      "src": "../../node_modules/react-query/devtools/index.js",
      "file": "react-query_devtools.js",
      "fileHash": "57a2c0a4",
      "needsInterop": true
    },
    "react-router-dom": {
      "src": "../../node_modules/react-router-dom/dist/index.js",
      "file": "react-router-dom.js",
      "fileHash": "9ec65a32",
      "needsInterop": false
    },
    "react-text-mask": {
      "src": "../../node_modules/react-text-mask/dist/reactTextMask.js",
      "file": "react-text-mask.js",
      "fileHash": "19c5bd99",
      "needsInterop": true
    },
    "socket.io-client": {
      "src": "../../node_modules/socket.io-client/build/esm/index.js",
      "file": "socket__io-client.js",
      "fileHash": "2a6bbc72",
      "needsInterop": false
    },
    "text-mask-addons": {
      "src": "../../node_modules/text-mask-addons/dist/textMaskAddons.js",
      "file": "text-mask-addons.js",
      "fileHash": "694172dd",
      "needsInterop": true
    },
    "yup": {
      "src": "../../node_modules/yup/index.esm.js",
      "file": "yup.js",
      "fileHash": "a6035b23",
      "needsInterop": false
    },
    "zustand": {
      "src": "../../node_modules/zustand/esm/index.mjs",
      "file": "zustand.js",
      "fileHash": "157158c3",
      "needsInterop": false
    }
  },
  "chunks": {
    "chunk-RPEOGDI4": {
      "file": "chunk-RPEOGDI4.js"
    },
    "chunk-VY2LOS32": {
      "file": "chunk-VY2LOS32.js"
    },
    "chunk-MXJCDWBI": {
      "file": "chunk-MXJCDWBI.js"
    },
    "chunk-SXG5K457": {
      "file": "chunk-SXG5K457.js"
    },
    "chunk-MM6YPM6B": {
      "file": "chunk-MM6YPM6B.js"
    },
    "chunk-KZI5IGQJ": {
      "file": "chunk-KZI5IGQJ.js"
    },
    "chunk-6EEL643C": {
      "file": "chunk-6EEL643C.js"
    },
    "chunk-7EJ2HHV3": {
      "file": "chunk-7EJ2HHV3.js"
    },
    "chunk-EZ23NLKT": {
      "file": "chunk-EZ23NLKT.js"
    },
    "chunk-NPHNUOFD": {
      "file": "chunk-NPHNUOFD.js"
    },
    "chunk-M6YSMIHL": {
      "file": "chunk-M6YSMIHL.js"
    },
    "chunk-B2HLYT6M": {
      "file": "chunk-B2HLYT6M.js"
    },
    "chunk-RYGAS6AX": {
      "file": "chunk-RYGAS6AX.js"
    },
    "chunk-XCERESLX": {
      "file": "chunk-XCERESLX.js"
    },
    "chunk-6QAH7EPR": {
      "file": "chunk-6QAH7EPR.js"
    },
    "chunk-Y3VRTV4G": {
      "file": "chunk-Y3VRTV4G.js"
    },
    "chunk-J32WSRGE": {
      "file": "chunk-J32WSRGE.js"
    }
  }
}